pwspider/__init__.py
pwspider-2.0.1.dist-info/METADATA
pwspider-2.0.1.dist-info/WHEEL
pwspider-2.0.1.dist-info/top_level.txt
pwspider-2.0.1.dist-info/RECORD
