Metadata-Version: 2.1
Name: pwspider
Version: 2.0.1
Summary: Tools for Spider
Home-page: https://github.com/pangwenhao326/FASTRequest/
Author: pw
Author-email: pangwen326@126.com
License: UNKNOWN
Platform: UNKNOWN
Classifier: Programming Language :: Python :: 3
Classifier: License :: OSI Approved :: MIT License
Classifier: Operating System :: OS Independent
Requires-Python: >=3.6
